claude_manager/__init__.py
claude_manager/__main__.py
claude_manager/_version.py
claude_manager/agent/__init__.py
claude_manager/agent/analyzer.py
claude_manager/agent/interactive.py
claude_manager/agent/schemas.py
claude_manager/agent/prompts/__init__.py
claude_manager/agent/prompts/analyze.py
claude_manager/agent/tools/__init__.py
claude_manager/cli/__init__.py
claude_manager/cli/analyze.py
claude_manager/cli/config.py
claude_manager/cli/hook.py
claude_manager/cli/library.py
claude_manager/cli/main.py
claude_manager/cli/mcp.py
claude_manager/cli/sync.py
claude_manager/core/__init__.py
claude_manager/core/differ.py
claude_manager/core/installer.py
claude_manager/core/paths.py
claude_manager/data/__init__.py
claude_manager/data/agents/_index.yaml
claude_manager/data/agents/global/architect.md
claude_manager/data/agents/global/code-reviewer.md
claude_manager/data/agents/global/commit.md
claude_manager/data/agents/global/debug-opus.md
claude_manager/data/agents/global/debug-sonnet.md
claude_manager/data/agents/global/doc.md
claude_manager/data/agents/global/tech-lead.md
claude_manager/data/agents/global/ux.md
claude_manager/data/agents/project/backend/go-opus.md
claude_manager/data/agents/project/backend/go.md
claude_manager/data/agents/project/backend/rust-opus.md
claude_manager/data/agents/project/backend/rust.md
claude_manager/data/agents/project/backend/spring-boot-opus.md
claude_manager/data/agents/project/backend/spring-boot-sonnet.md
claude_manager/data/agents/project/database/postgresql-opus.md
claude_manager/data/agents/project/database/postgresql-sonnet.md
claude_manager/data/agents/project/devops/docker.md
claude_manager/data/agents/project/devops/gitlab-ci.md
claude_manager/data/agents/project/devops/keycloak.md
claude_manager/data/agents/project/devops/terraform.md
claude_manager/data/agents/project/frontend/svelte.md
claude_manager/data/agents/project/frontend/vue3.md
claude_manager/data/agents/project/quality/playwright.md
claude_manager-0.4.0.dist-info/METADATA
claude_manager-0.4.0.dist-info/WHEEL
claude_manager-0.4.0.dist-info/entry_points.txt
claude_manager-0.4.0.dist-info/licenses/LICENSE.md
claude_manager-0.4.0.dist-info/RECORD
